{"metadata": {"dbt_schema_version": "https://schemas.getdbt.com/dbt/catalog/v1.json", "dbt_version": "1.6.3", "generated_at": "2023-12-12T10:20:13.290093Z", "invocation_id": "3599c71e-8d28-482e-9c4c-cca7f4146109", "env": {}}, "nodes": {"model.template_by_vitlamdata.analytics_jira_ticket": {"metadata": {"type": "table", "schema": "jira_clv_analytics", "name": "analytics_jira_ticket", "database": "looker-team-management-386803", "comment": null, "owner": null}, "columns": {"ticket_key": {"type": "STRING", "index": 1, "name": "ticket_key", "comment": null}, "sprint": {"type": "STRING", "index": 2, "name": "sprint", "comment": null}, "ticket_status": {"type": "STRING", "index": 3, "name": "ticket_status", "comment": null}, "parent_ticket_key": {"type": "STRING", "index": 4, "name": "parent_ticket_key", "comment": null}, "is_parent": {"type": "BOOL", "index": 5, "name": "is_parent", "comment": null}, "is_delayed_task": {"type": "BOOL", "index": 6, "name": "is_delayed_task", "comment": null}, "ticket_name": {"type": "STRING", "index": 7, "name": "ticket_name", "comment": null}, "update_date": {"type": "TIMESTAMP", "index": 8, "name": "update_date", "comment": null}, "assignee": {"type": "STRING", "index": 9, "name": "assignee", "comment": null}, "end_date": {"type": "DATE", "index": 10, "name": "end_date", "comment": null}, "ticket_type": {"type": "STRING", "index": 11, "name": "ticket_type", "comment": null}, "start_date": {"type": "DATE", "index": 12, "name": "start_date", "comment": null}, "story_points": {"type": "NUMERIC", "index": 13, "name": "story_points", "comment": null}, "update_iteration": {"type": "STRING", "index": 14, "name": "update_iteration", "comment": null}, "is_current_row": {"type": "BOOL", "index": 15, "name": "is_current_row", "comment": null}}, "stats": {"num_rows": {"id": "num_rows", "label": "# Rows", "value": 10715, "include": true, "description": "Approximate count of rows in this table"}, "num_bytes": {"id": "num_bytes", "label": "Approximate Size", "value": 1889037, "include": true, "description": "Approximate size of table as reported by BigQuery"}, "has_stats": {"id": "has_stats", "label": "Has Stats?", "value": true, "include": false, "description": "Indicates whether there are statistics for this table"}}, "unique_id": "model.template_by_vitlamdata.analytics_jira_ticket"}}, "sources": {}, "errors": null}